manager_utils/__init__.py
manager_utils/apps.py
manager_utils/manager_utils.py
manager_utils/upsert2.py
manager_utils/version.py
manager_utils/tests/__init__.py
manager_utils/tests/manager_utils_tests.py
manager_utils/tests/models.py
django_manager_utils-3.1.5.dist-info/LICENSE
django_manager_utils-3.1.5.dist-info/METADATA
django_manager_utils-3.1.5.dist-info/WHEEL
django_manager_utils-3.1.5.dist-info/top_level.txt
django_manager_utils-3.1.5.dist-info/RECORD
