Metadata-Version: 2.1
Name: django-manager-utils
Version: 3.1.5
Summary: Model manager utilities for Django
Home-page: http://github.com/ambitioninc/django-manager-utils/
Author: Wes Kendall
Author-email: opensource@ambition.com
License: UNKNOWN
Project-URL: Bug Tracker, https://github.com/ambitioninc/django-manager-utils/issues
Project-URL: Changes, https://django-manager-utils.readthedocs.io/en/latest/release_notes.html
Project-URL: Documentation, https://django-manager-utils.readthedocs.io/en/latest/
Project-URL: Source Code, https://github.com/ambitioninc/django-manager-utils
Platform: UNKNOWN
Classifier: Programming Language :: Python
Classifier: Programming Language :: Python :: 3.7
Classifier: Programming Language :: Python :: 3.8
Classifier: Programming Language :: Python :: 3.9
Classifier: Intended Audience :: Developers
Classifier: License :: OSI Approved :: MIT License
Classifier: Operating System :: OS Independent
Classifier: Framework :: Django :: 3.2
Classifier: Framework :: Django :: 4.0
Classifier: Framework :: Django :: 4.1
Classifier: Framework :: Django :: 4.2
License-File: LICENSE
Requires-Dist: Django >=3.2
Requires-Dist: django-query-builder >=3.1.0
